bericht/__init__.py
bericht/html/__init__.py
bericht/html/box.py
bericht/html/css.py
bericht/html/html.css
bericht/html/parser.py
bericht/html/style.py
bericht/html/table.py
bericht/pdf/__init__.py
bericht/pdf/document.py
bericht/pdf/font.py
bericht/pdf/letterhead.py
bericht/pdf/page.py
bericht/pdf/reference.py
bericht/pdf/stream.py
bericht/pdf/text.py
bericht-0.1.6.dist-info/DESCRIPTION.rst
bericht-0.1.6.dist-info/METADATA
bericht-0.1.6.dist-info/RECORD
bericht-0.1.6.dist-info/WHEEL
bericht-0.1.6.dist-info/metadata.json
bericht-0.1.6.dist-info/top_level.txt
tests/__init__.py
tests/test_fonts.py
tests/test_html_box.py
tests/test_html_css.py
tests/test_html_table.py
tests/test_pdf.py
tests/test_style.py
tests/test_table.py
tests/test_text.py
tests/utils.py
