Metadata-Version: 2.0
Name: bericht
Version: 0.1.6
Summary: HTML to PDF streaming
Home-page: https://github.com/systori/bericht
Author: Lex Berezhny
Author-email: lex@damoti.com
License: BSD
Keywords: pdf,table,report,html
Platform: UNKNOWN
Classifier: Intended Audience :: Developers
Classifier: License :: OSI Approved :: BSD License
Classifier: Programming Language :: Python :: 3
Classifier: Operating System :: OS Independent
Classifier: Topic :: Software Development :: Libraries :: Python Modules
Classifier: Topic :: Software Development :: User Interfaces
Requires-Dist: reportlab
Requires-Dist: pdfrw
Requires-Dist: tinycss2
Requires-Dist: lxml
